agentic_crew/__init__.py
agentic_crew/__main__.py
agentic_crew/crew.py
agentic_crew/main.py
agentic_crew/run_flow.py
agentic_crew/base/__init__.py
agentic_crew/base/archetypes.yaml
agentic_crew/config/__init__.py
agentic_crew/config/agents.yaml
agentic_crew/config/llm.py
agentic_crew/config/tasks.yaml
agentic_crew/core/__init__.py
agentic_crew/core/decomposer.py
agentic_crew/core/discovery.py
agentic_crew/core/loader.py
agentic_crew/core/runner.py
agentic_crew/runners/__init__.py
agentic_crew/runners/base.py
agentic_crew/runners/crewai_runner.py
agentic_crew/runners/langgraph_runner.py
agentic_crew/runners/local_cli_profiles.yaml
agentic_crew/runners/strands_runner.py
agentic_crew/tools/__init__.py
agentic_crew/tools/file_tools.py
agentic_crew-0.2.0.dist-info/METADATA
agentic_crew-0.2.0.dist-info/WHEEL
agentic_crew-0.2.0.dist-info/entry_points.txt
agentic_crew-0.2.0.dist-info/RECORD
