Metadata-Version: 2.4
Name: agentic-crew
Version: 0.2.0
Summary: Framework-agnostic AI crew orchestration - declare once, run on CrewAI, LangGraph, or Strands
Project-URL: Homepage, https://github.com/jbcom/agentic-crew
Project-URL: Repository, https://github.com/jbcom/agentic-crew
Project-URL: Documentation, https://github.com/jbcom/agentic-crew#readme
Project-URL: Issues, https://github.com/jbcom/agentic-crew/issues
Author-email: Jon Bogaty <jon@jonbogaty.com>
License: MIT
Keywords: ai-agents,crewai,langgraph,multi-agent,orchestration,strands
Classifier: Development Status :: 4 - Beta
Classifier: Intended Audience :: Developers
Classifier: License :: OSI Approved :: MIT License
Classifier: Programming Language :: Python :: 3.11
Classifier: Programming Language :: Python :: 3.12
Classifier: Programming Language :: Python :: 3.13
Requires-Python: >=3.11
Requires-Dist: pydantic>=2.12.4
Requires-Dist: pyyaml>=6.0.3
Provides-Extra: ai
Requires-Dist: crewai[anthropic,tools]>=1.5.0; extra == 'ai'
Requires-Dist: langchain-anthropic>=0.3.0; extra == 'ai'
Requires-Dist: langgraph>=0.2.0; extra == 'ai'
Requires-Dist: strands-agents>=0.1.0; extra == 'ai'
Provides-Extra: all
Requires-Dist: beautifulsoup4>=4.12.0; extra == 'all'
Requires-Dist: crewai[anthropic,tools]>=1.5.0; extra == 'all'
Requires-Dist: langchain-anthropic>=0.3.0; extra == 'all'
Requires-Dist: langgraph>=0.2.0; extra == 'all'
Requires-Dist: mcp>=1.0.0; extra == 'all'
Requires-Dist: strands-agents>=0.1.0; extra == 'all'
Requires-Dist: vendor-connectors[meshy]>=0.2.0; extra == 'all'
Provides-Extra: crewai
Requires-Dist: crewai[anthropic,tools]>=1.5.0; extra == 'crewai'
Provides-Extra: dev
Requires-Dist: mypy>=1.8.0; extra == 'dev'
Requires-Dist: ruff>=0.1.0; extra == 'dev'
Provides-Extra: docs
Requires-Dist: myst-parser>=3.0.0; extra == 'docs'
Requires-Dist: sphinx-autodoc-typehints>=2.0.0; extra == 'docs'
Requires-Dist: sphinx-rtd-theme>=2.0.0; extra == 'docs'
Requires-Dist: sphinx>=7.0.0; extra == 'docs'
Provides-Extra: langgraph
Requires-Dist: langchain-anthropic>=0.3.0; extra == 'langgraph'
Requires-Dist: langgraph>=0.2.0; extra == 'langgraph'
Provides-Extra: mcp
Requires-Dist: mcp>=1.0.0; extra == 'mcp'
Provides-Extra: meshy
Requires-Dist: vendor-connectors[meshy]>=0.2.0; extra == 'meshy'
Provides-Extra: scraping
Requires-Dist: beautifulsoup4>=4.12.0; extra == 'scraping'
Requires-Dist: crewai[tools]>=1.5.0; extra == 'scraping'
Provides-Extra: strands
Requires-Dist: strands-agents>=0.1.0; extra == 'strands'
Provides-Extra: tests
Requires-Dist: pytest-asyncio>=0.23.0; extra == 'tests'
Requires-Dist: pytest-cov>=5.0.0; extra == 'tests'
Requires-Dist: pytest-mock>=3.15.1; extra == 'tests'
Requires-Dist: pytest-timeout>=2.4.0; extra == 'tests'
Requires-Dist: pytest>=9.0.1; extra == 'tests'
